Metadata-Version: 1.0
Name: wsearch
Version: 0.0.1.1
Summary: a search engine crwaler based on python, can be easily configed
Home-page: https://github.com/wvinzh/WutongSearch
Author: wvinzh
Author-email: wvinzh@qq.com
License: Apache Licence 2.0
Keywords: search engine,crawler
Platform: any
